celery_statsd/__about__.py
celery_statsd/__init__.py
celery_statsd-1.0.0.dist-info/DESCRIPTION.rst
celery_statsd-1.0.0.dist-info/METADATA
celery_statsd-1.0.0.dist-info/RECORD
celery_statsd-1.0.0.dist-info/WHEEL
celery_statsd-1.0.0.dist-info/metadata.json
celery_statsd-1.0.0.dist-info/top_level.txt
