Metadata-Version: 2.0
Name: celery-statsd
Version: 1.0.0
Summary: Send various info to statsd for each Celery task
Home-page: https://github.com/lyst/celery-statsd/
Author: Lyst LTD
Author-email: info@lyst.com
License: LGPLv3
Platform: UNKNOWN
Requires-Dist: celery (>=3.1.17)
Requires-Dist: statsd (>=3.0)
Requires-Dist: six (>=1.9.0)
